app/__init__.py
app/cli.py
app/main.py
app/utils.py
CLI_EXPORTER-0.1.0.dist-info/METADATA
CLI_EXPORTER-0.1.0.dist-info/WHEEL
CLI_EXPORTER-0.1.0.dist-info/entry_points.txt
CLI_EXPORTER-0.1.0.dist-info/top_level.txt
CLI_EXPORTER-0.1.0.dist-info/RECORD
