Metadata-Version: 2.1
Name: CLI-EXPORTER
Version: 0.1.0
Summary: CLI application to automate data extraction and formating for Bitwarden csv import
Author: Rachmann Joubert
Classifier: Programming Language :: Python :: 3
Classifier: License :: OSI Approved :: MIT License
Classifier: Operating System :: OS Independent
Requires-Python: >=3.6
Requires-Dist: click
Requires-Dist: pandas
Requires-Dist: python-docx
